emailme/__init__.py
emailme/cli.py
emailme/functions.py
emailme-0.3.0.dist-info/LICENSE
emailme-0.3.0.dist-info/METADATA
emailme-0.3.0.dist-info/WHEEL
emailme-0.3.0.dist-info/entry_points.txt
emailme-0.3.0.dist-info/top_level.txt
emailme-0.3.0.dist-info/RECORD
