Metadata-Version: 2.1
Name: emailme
Version: 0.3.0
Summary: Super simple self-emailing.
Home-page: http://github.com/ericmjl/emailme
Author: Eric J. Ma
Author-email: ericmajinglong@gmail.com
License: MIT
Keywords: email
Platform: UNKNOWN
Requires-Dist: click (>=7.0)
Requires-Dist: colorama (==0.3.9)
Requires-Dist: python-dotenv (==0.13.0)
Requires-Dist: streamlit
